mylib_010/__init__.py
mylib_010-0.1.dist-info/LICENCE.txt
mylib_010-0.1.dist-info/METADATA
mylib_010-0.1.dist-info/WHEEL
mylib_010-0.1.dist-info/top_level.txt
mylib_010-0.1.dist-info/RECORD
