Metadata-Version: 2.1
Name: mylib-010
Version: 0.1
Summary: for calculating cube
Author: Ankur
Author-email: vy8655@gmail.com
Classifier: Programming Language :: Python :: 3
Classifier: License :: OSI Approved :: MIT License
Classifier: Operating System :: OS Independent
License-File: LICENCE.txt
